recorder/__init__.py
recorder/recorder.py
lamda_recorder-0.2.3.dist-info/METADATA
lamda_recorder-0.2.3.dist-info/WHEEL
lamda_recorder-0.2.3.dist-info/top_level.txt
lamda_recorder-0.2.3.dist-info/RECORD
