Metadata-Version: 2.1
Name: lamda-recorder
Version: 0.2.3
Summary: recorder for machine learning
Home-page: https://github.com/pypa/sampleproject
Author: Haoyuan He
Author-email: hehy@lamda.nju.edu.cn
License: UNKNOWN
Platform: UNKNOWN
Classifier: Programming Language :: Python :: 3
Classifier: License :: OSI Approved :: MIT License
Classifier: Operating System :: OS Independent
Requires-Dist: prettytable
Requires-Dist: numpy
Requires-Dist: pandas
